ppm_display/__init__.py
ppm_display/ppm_disp.py
ppm_display-1.1.3.dist-info/LICENSE
ppm_display-1.1.3.dist-info/METADATA
ppm_display-1.1.3.dist-info/WHEEL
ppm_display-1.1.3.dist-info/entry_points.txt
ppm_display-1.1.3.dist-info/top_level.txt
ppm_display-1.1.3.dist-info/RECORD
