Metadata-Version: 2.1
Name: ppm-display
Version: 1.1.3
Summary: PPM/PGM image viewer
Home-page: https://github.com/Trenza1ore/ppm-display
Author: Hugo (Jin Huang)
Author-email: s2050808@ed.ac.uk
License: MIT
Keywords: ppm pgm image python package ppm-display ppm-disp
Classifier: Programming Language :: Python :: 3
Classifier: License :: OSI Approved :: MIT License
Classifier: Operating System :: OS Independent
License-File: LICENSE
Requires-Dist: opencv-python (>=3.4.0.14)
Requires-Dist: docopt (>=0.6.2)
